docs/unidade5_cap3_contador/sync_counter.sv
// =============================================================================
// sync_counter.sv -- Contador Sincrono de 4 bits
// Unidade 5 | Capitulo 3 | Capacitacao Profissional em Microeletronica (PADIS)
// Autor : Matheus Serrao Uchoa   Matricula: 22052633
// Prof. : Thiago Brito
// Data  : Maio 2026
// =============================================================================
// Funcionalidades:
//   - Contagem crescente (up-counter): incrementa em 1 a cada borda de clock
//   - Reset assincrono ativo em nivel baixo (rst_n): zera imediatamente
//   - Enable sincrono ativo em nivel alto (en): incrementa somente se en=1
//   - Overflow: cicla de 15 (4'b1111) para 0 (4'b0000) automaticamente
// =============================================================================

module sync_counter (
    input  logic       clk,        // clock (borda de subida)
    input  logic       rst_n,      // reset assincrono ativo baixo
    input  logic       en,         // enable sincrono ativo alto
    output logic [3:0] count       // valor atual do contador (0..15)
);

    // Logica sequencial: reset assincrono + enable sincrono + overflow natural
    always_ff @(posedge clk or negedge rst_n) begin
        if (!rst_n)
            count <= 4'b0000;      // reset assincrono: zera imediatamente
        else if (en)
            count <= count + 1'b1; // incremento sincrono (overflow automatico: 15->0)
        // se en=0: count mantem valor (sem else => sem latch em always_ff)
    end

endmodule

docs/unidade5_cap3_contador/tb_sync_counter.sv
// =============================================================================
// tb_sync_counter.sv -- Testbench para sync_counter
// Unidade 5 | Capitulo 3 | Capacitacao Profissional em Microeletronica (PADIS)
// Autor : Matheus Serrao Uchoa   Matricula: 22052633
// Prof. : Thiago Brito
// =============================================================================
`timescale 1ns/1ps

module tb_sync_counter;

    // -------------------------------------------------------------------------
    // Sinais
    // -------------------------------------------------------------------------
    logic       clk;
    logic       rst_n;
    logic       en;
    logic [3:0] count;

    int erros  = 0;
    int acertos = 0;

    // -------------------------------------------------------------------------
    // Instanciacao do DUT
    // -------------------------------------------------------------------------
    sync_counter dut (
        .clk   (clk),
        .rst_n (rst_n),
        .en    (en),
        .count (count)
    );

    // -------------------------------------------------------------------------
    // Clock: periodo 10 ns (50 MHz)
    // -------------------------------------------------------------------------
    initial clk = 0;
    always #5 clk = ~clk;

    // -------------------------------------------------------------------------
    // Monitor continuo: imprime toda mudanca relevante
    // -------------------------------------------------------------------------
    initial begin
        $monitor("t=%4t ns | clk=%b rst_n=%b en=%b | count=%02d (4'b%04b)",
                 $time, clk, rst_n, en, count, count);
    end

    // -------------------------------------------------------------------------
    // Tarefa: verifica valor esperado apos posedge
    // -------------------------------------------------------------------------
    task automatic verifica(
        input logic [3:0] esperado,
        input string      descricao
    );
        @(posedge clk); #1;
        if (count !== esperado) begin
            $display("  [FALHA] %s | count=%0d | Esperado=%0d", descricao, count, esperado);
            erros++;
        end else begin
            $display("  [OK]    %s | count=%0d", descricao, count);
            acertos++;
        end
    endtask

    // -------------------------------------------------------------------------
    // Tarefa: avanca N ciclos de clock sem verificacao
    // -------------------------------------------------------------------------
    task automatic aguarda(input int n);
        repeat(n) @(posedge clk);
        #1;
    endtask

    // -------------------------------------------------------------------------
    // Sequencia de testes
    // -------------------------------------------------------------------------
    initial begin
        $dumpfile("dump_counter.vcd");
        $dumpvars(0, tb_sync_counter);

        $display("========================================================");
        $display("  Simulacao: Contador Sincrono 4 bits");
        $display("  Sequencia: rst_n / enable / disable / overflow / reset");
        $display("========================================================\n");

        // ------------------------------------------------------------------
        // TESTE 1: Reset assincrono
        // ------------------------------------------------------------------
        $display("--- TESTE 1: Reset assincrono (rst_n = 0) ---");
        rst_n = 0; en = 0;
        #3; // reset assincrono: conta deve ser 0 imediatamente (sem esperar clock)
        if (count !== 4'b0000) begin
            $display("  [FALHA] Reset assincrono: count=%0d esperado=0", count); erros++;
        end else begin
            $display("  [OK]    Reset assincrono imediato: count=0"); acertos++;
        end
        @(posedge clk); #1;
        rst_n = 1;

        // ------------------------------------------------------------------
        // TESTE 2: Enable sincrono -- conta de 0 a 7
        // ------------------------------------------------------------------
        $display("\n--- TESTE 2: Enable sincrono (en=1), conta 0->7 ---");
        en = 1;
        verifica(4'd1,  "en=1, ciclo  1");
        verifica(4'd2,  "en=1, ciclo  2");
        verifica(4'd3,  "en=1, ciclo  3");
        verifica(4'd4,  "en=1, ciclo  4");
        verifica(4'd5,  "en=1, ciclo  5");
        verifica(4'd6,  "en=1, ciclo  6");
        verifica(4'd7,  "en=1, ciclo  7");

        // ------------------------------------------------------------------
        // TESTE 3: Desabilitar contador (en=0), count deve manter valor
        // ------------------------------------------------------------------
        $display("\n--- TESTE 3: Enable desativado (en=0), count congela em 7 ---");
        en = 0;
        verifica(4'd7,  "en=0, ciclo  1 (congela)");
        verifica(4'd7,  "en=0, ciclo  2 (congela)");
        verifica(4'd7,  "en=0, ciclo  3 (congela)");

        // ------------------------------------------------------------------
        // TESTE 4: Reativar enable -- continua de 7
        // ------------------------------------------------------------------
        $display("\n--- TESTE 4: Reativa en=1, continua de 7 ---");
        en = 1;
        verifica(4'd8,  "en=1 reativado, count=8");
        verifica(4'd9,  "en=1, count=9");
        verifica(4'd10, "en=1, count=10");

        // ------------------------------------------------------------------
        // TESTE 5: Toggle enable durante contagem
        // ------------------------------------------------------------------
        $display("\n--- TESTE 5: Toggle en durante contagem ---");
        en = 0; verifica(4'd10, "en=0, count congela 10");
        en = 1; verifica(4'd11, "en=1, count=11");
        en = 0; verifica(4'd11, "en=0, count congela 11");
        en = 1; verifica(4'd12, "en=1, count=12");

        // ------------------------------------------------------------------
        // TESTE 6: Contagem ate overflow (12 -> 15 -> 0)
        // ------------------------------------------------------------------
        $display("\n--- TESTE 6: Overflow (15 -> 0) ---");
        verifica(4'd13, "count=13");
        verifica(4'd14, "count=14");
        verifica(4'd15, "count=15 (maximo)");
        verifica(4'd0,  "overflow: count=0");
        verifica(4'd1,  "pos-overflow: count=1");

        // ------------------------------------------------------------------
        // TESTE 7: Reset assincrono durante contagem ativa
        // ------------------------------------------------------------------
        $display("\n--- TESTE 7: Reset assincrono durante contagem ativa ---");
        en = 1;
        aguarda(3);
        // Aplica reset no meio do ciclo (nao na borda)
        #3; rst_n = 0;
        #1;
        if (count !== 4'b0000) begin
            $display("  [FALHA] Reset assincrono mid-cycle: count=%0d esperado=0", count); erros++;
        end else begin
            $display("  [OK]    Reset assincrono mid-cycle: count=0 imediato"); acertos++;
        end
        @(posedge clk); #1;
        rst_n = 1;
        verifica(4'd1, "apos reset, continua contagem: count=1");
        verifica(4'd2, "count=2");

        // ------------------------------------------------------------------
        // RESULTADO FINAL
        // ------------------------------------------------------------------
        $display("\n========================================================");
        $display("  Acertos: %0d | Erros: %0d", acertos, erros);
        if (erros == 0)
            $display("  >>> RESULTADO: APROVADO <<<");
        else
            $display("  >>> RESULTADO: REPROVADO -- %0d erro(s) <<<", erros);
        $display("  Simulacao concluida em %0t", $time);
        $display("========================================================");
        $finish;
    end

endmodule

docs/unidade5_cap3_contador/dump_counter.vcd
$date
	Tue May 12 05:12:32 2026
$end
$version
	Icarus Verilog
$end
$timescale
	1ps
$end
$scope module tb_sync_counter $end
$var wire 4 ! count [3:0] $end
$var reg 1 " clk $end
$var reg 1 # en $end
$var reg 1 $ rst_n $end
$var integer 32 % acertos [31:0] $end
$var integer 32 & erros [31:0] $end
$scope module dut $end
$var wire 1 " clk $end
$var wire 1 # en $end
$var wire 1 $ rst_n $end
$var reg 4 ' count [3:0] $end
$upscope $end
$scope task aguarda $end
$upscope $end
$scope task verifica $end
$upscope $end
$upscope $end
$enddefinitions $end
$comment Show the parameter values. $end
$dumpall
$end
#0
$dumpvars
b0 '
b0 &
b0 %
0$
0#
0"
b0 !
$end
#3000
b1 %
#5000
1"
#6000
1#
1$
#10000
0"
#15000
b1 !
b1 '
1"
#16000
b10 %
#20000
0"
#25000
b10 !
b10 '
1"
#26000
b11 %
#30000
0"
#35000
b11 !
b11 '
1"
#36000
b100 %
#40000
0"
#45000
b100 !
b100 '
1"
#46000
b101 %
#50000
0"
#55000
b101 !
b101 '
1"
#56000
b110 %
#60000
0"
#65000
b110 !
b110 '
1"
#66000
b111 %
#70000
0"
#75000
b111 !
b111 '
1"
#76000
0#
b1000 %
#80000
0"
#85000
1"
#86000
b1001 %
#90000
0"
#95000
1"
#96000
b1010 %
#100000
0"
#105000
1"
#106000
1#
b1011 %
#110000
0"
#115000
b1000 !
b1000 '
1"
#116000
b1100 %
#120000
0"
#125000
b1001 !
b1001 '
1"
#126000
b1101 %
#130000
0"
#135000
b1010 !
b1010 '
1"
#136000
0#
b1110 %
#140000
0"
#145000
1"
#146000
1#
b1111 %
#150000
0"
#155000
b1011 !
b1011 '
1"
#156000
0#
b10000 %
#160000
0"
#165000
1"
#166000
1#
b10001 %
#170000
0"
#175000
b1100 !
b1100 '
1"
#176000
b10010 %
#180000
0"
#185000
b1101 !
b1101 '
1"
#186000
b10011 %
#190000
0"
#195000
b1110 !
b1110 '
1"
#196000
b10100 %
#200000
0"
#205000
b1111 !
b1111 '
1"
#206000
b10101 %
#210000
0"
#215000
b0 !
b0 '
1"
#216000
b10110 %
#220000
0"
#225000
b1 !
b1 '
1"
#226000
b10111 %
#230000
0"
#235000
b10 !
b10 '
1"
#240000
0"
#245000
b11 !
b11 '
1"
#250000
0"
#255000
b100 !
b100 '
1"
#259000
b0 !
b0 '
0$
#260000
b11000 %
0"
#265000
1"
#266000
1$
#270000
0"
#275000
b1 !
b1 '
1"
#276000
b11001 %
#280000
0"
#285000
b10 !
b10 '
1"
#286000
b11010 %
