docs/unidade7_cap5_desafio_romulo/alu8.sv
// =============================================================================
// alu8.sv -- ALUChip v1.0: Unidade Logico-Aritmetica de 8 bits
// Unidade 7 | Capitulo 5 | PADIS
// Autor : Romulo da Silva Lira
// Prof. : Andre Feitosa
// =============================================================================
// Operacoes (op[2:0]):
//   000 ADD  -- A + B              (atualiza C, V)
//   001 SUB  -- A - B              (atualiza C, V)
//   010 AND  -- A & B
//   011 OR   -- A | B
//   100 XOR  -- A ^ B
//   101 NOT  -- ~A
//   110 SHL  -- A << 1, LSB=0, C=A[7]
//   111 SHR  -- A >> 1, MSB=0, C=A[0]
//
// Flags:
//   Z -- Zero      : result == 8'h00
//   C -- Carry     : carry-out / shift-out
//   V -- Overflow  : estouro de sinal (so ADD/SUB)
//   N -- Negativo  : result[7]
// =============================================================================

module alu8 (
    input  logic [7:0] a,          // operando A
    input  logic [7:0] b,          // operando B
    input  logic [2:0] op,         // codigo da operacao
    output logic [7:0] result,     // resultado de 8 bits
    output logic       flag_z,     // Zero
    output logic       flag_c,     // Carry / borrow / shift-out
    output logic       flag_v,     // Overflow (sinal)
    output logic       flag_n      // Negativo (MSB do resultado)
);

    logic [8:0] wide;   // 9 bits: [8]=carry, [7:0]=result

    // Bits extraidos para compatibilidade com Icarus (constant selects)
    logic       a_msb;   // a[7]
    logic       b_msb;   // b[7]
    logic       a_lsb;   // a[0]
    logic [6:0] a_lo7;   // a[6:0]
    logic [6:0] a_hi7;   // a[7:1]
    assign a_msb = a[7];
    assign b_msb = b[7];
    assign a_lsb = a[0];
    assign a_lo7 = a[6:0];
    assign a_hi7 = a[7:1];

    always_comb begin
        case (op)
            3'b000: wide = {1'b0, a} + {1'b0, b};          // ADD
            3'b001: wide = {1'b0, a} + {1'b0, ~b} + 9'd1;  // SUB
            3'b010: wide = {1'b0, a & b};                   // AND
            3'b011: wide = {1'b0, a | b};                   // OR
            3'b100: wide = {1'b0, a ^ b};                   // XOR
            3'b101: wide = {1'b0, ~a};                      // NOT
            3'b110: wide = {a_msb, a_lo7, 1'b0};            // SHL
            3'b111: wide = {a_lsb, 1'b0, a_hi7};            // SHR
            default: wide = 9'b0;
        endcase
    end

    // Overflow calculado fora do always_comb para evitar bit-selects internos
    logic res_msb;
    assign res_msb = wide[7];
    assign flag_v  = ((op == 3'b000) & ((~a_msb & ~b_msb &  res_msb) |
                                         ( a_msb &  b_msb & ~res_msb))) |
                     ((op == 3'b001) & ((~a_msb &  b_msb &  res_msb) |
                                         ( a_msb & ~b_msb & ~res_msb)));

    assign result = wide[7:0];
    assign flag_c = wide[8];
    assign flag_z = (wide[7:0] == 8'h00);
    assign flag_n = wide[7];

endmodule

docs/unidade7_cap5_desafio_romulo/alu8_chip_top.sv
// =============================================================================
// alu8_chip_top.sv -- Top-level: ALUChip v1.0
// Unidade Logico-Aritmetica de 8 bits
// Unidade 7 | Capitulo 5 | PADIS
// Autor : Romulo da Silva Lira
// Prof. : Andre Feitosa
// =============================================================================
// Hierarquia:
//   alu8_chip_top
//   └── alu8  -- ULA combinacional 8 bits / 8 operacoes / 4 flags
//
// Especificacoes:
//   Processo : CMOS 0.35um | VDD = 3.3V
//   Funcao   : ULA 8 bits -- ADD, SUB, AND, OR, XOR, NOT, SHL, SHR
//   Latencia : 0 ciclos (logica puramente combinacional)
//   Aplicacao: Nucleo aritmetico de microprocessadores, DSP, controladores
// =============================================================================

module alu8_chip_top (
    input  logic [7:0] a,        // operando A
    input  logic [7:0] b,        // operando B
    input  logic [2:0] op,       // selecao de operacao (000..111)
    output logic [7:0] result,   // resultado de 8 bits
    output logic       flag_z,   // Zero
    output logic       flag_c,   // Carry / Borrow / Shift-out
    output logic       flag_v,   // Overflow (sinal)
    output logic       flag_n    // Negativo
);

    alu8 u_alu (
        .a       (a),
        .b       (b),
        .op      (op),
        .result  (result),
        .flag_z  (flag_z),
        .flag_c  (flag_c),
        .flag_v  (flag_v),
        .flag_n  (flag_n)
    );

endmodule

docs/unidade7_cap5_desafio_romulo/tb_alu8_chip.sv
// =============================================================================
// tb_alu8_chip.sv -- Testbench: ALUChip v1.0
// Unidade 7 | Capitulo 5 | PADIS
// Autor : Romulo da Silva Lira
// =============================================================================
`timescale 1ns/1ps

module tb_alu8_chip;

    // Operacoes
    localparam OP_ADD = 3'b000;
    localparam OP_SUB = 3'b001;
    localparam OP_AND = 3'b010;
    localparam OP_OR  = 3'b011;
    localparam OP_XOR = 3'b100;
    localparam OP_NOT = 3'b101;
    localparam OP_SHL = 3'b110;
    localparam OP_SHR = 3'b111;

    logic [7:0] a, b;
    logic [2:0] op;
    logic [7:0] result;
    logic       flag_z, flag_c, flag_v, flag_n;

    int erros  = 0;
    int testes = 0;

    alu8_chip_top dut (.*);

    // -------------------------------------------------------------------------
    task automatic testa(
        input logic [7:0] ea, eb,
        input logic [2:0] eop,
        input logic [7:0] exp_result,
        input logic exp_z, exp_c, exp_v, exp_n,
        input string descricao
    );
        string op_str;
        case (eop)
            OP_ADD: op_str = "ADD";
            OP_SUB: op_str = "SUB";
            OP_AND: op_str = "AND";
            OP_OR:  op_str = "OR ";
            OP_XOR: op_str = "XOR";
            OP_NOT: op_str = "NOT";
            OP_SHL: op_str = "SHL";
            OP_SHR: op_str = "SHR";
            default: op_str = "???";
        endcase

        a = ea; b = eb; op = eop;
        #2;
        testes++;

        if (result !== exp_result || flag_z !== exp_z ||
            flag_c !== exp_c || flag_v !== exp_v || flag_n !== exp_n) begin
            $display("  [FALHA] %s %s | A=%02X B=%02X | res=%02X exp=%02X | Z%b C%b V%b N%b exp:Z%b C%b V%b N%b",
                op_str, descricao, ea, eb,
                result, exp_result,
                flag_z, flag_c, flag_v, flag_n,
                exp_z, exp_c, exp_v, exp_n);
            erros++;
        end else begin
            $display("  [OK] %s %s | %02Xh %s %02Xh = %02Xh | Z=%b C=%b V=%b N=%b",
                op_str, descricao, ea,
                (eop == OP_NOT || eop == OP_SHL || eop == OP_SHR) ? "  " :
                (eop == OP_ADD) ? "+" :
                (eop == OP_SUB) ? "-" :
                (eop == OP_AND) ? "&" :
                (eop == OP_OR)  ? "|" : "^",
                eb, result, flag_z, flag_c, flag_v, flag_n);
        end
    endtask

    // -------------------------------------------------------------------------
    initial begin
        $dumpfile("dump_alu.vcd");
        $dumpvars(0, tb_alu8_chip);

        $display("======================================================");
        $display(" ALUChip v1.0 -- ULA 8 bits (8 operacoes / 4 flags)");
        $display(" Simulacao Funcional");
        $display(" Processo: CMOS 0.35um | VDD=3.3V");
        $display("======================================================");

        // ----- ADD -----
        $display("\n--- ADD ---");
        testa(8'h03, 8'h05, OP_ADD, 8'h08, 0,0,0,0, "3+5=8");
        testa(8'hFF, 8'h01, OP_ADD, 8'h00, 1,1,0,0, "FF+01=00 (carry, zero)");
        testa(8'h7F, 8'h01, OP_ADD, 8'h80, 0,0,1,1, "7F+01=80 (overflow)");
        testa(8'h80, 8'h80, OP_ADD, 8'h00, 1,1,1,0, "80+80=00 (carry+overflow)");
        testa(8'hA0, 8'h30, OP_ADD, 8'hD0, 0,0,0,1, "A0+30=D0 (negativo)");

        // ----- SUB -----
        $display("\n--- SUB ---");
        testa(8'h08, 8'h03, OP_SUB, 8'h05, 0,1,0,0, "8-3=5");
        testa(8'h03, 8'h08, OP_SUB, 8'hFB, 0,0,0,1, "3-8=FB (negativo)");
        testa(8'h00, 8'h01, OP_SUB, 8'hFF, 0,0,0,1, "0-1=FF (borrow)");
        testa(8'h80, 8'h01, OP_SUB, 8'h7F, 0,1,1,0, "80-01=7F (overflow)");
        testa(8'h40, 8'h40, OP_SUB, 8'h00, 1,1,0,0, "40-40=00 (zero)");

        // ----- AND -----
        $display("\n--- AND ---");
        testa(8'hFF, 8'h0F, OP_AND, 8'h0F, 0,0,0,0, "FF&0F=0F");
        testa(8'hAA, 8'h55, OP_AND, 8'h00, 1,0,0,0, "AA&55=00 (zero)");
        testa(8'hF0, 8'hF0, OP_AND, 8'hF0, 0,0,0,1, "F0&F0=F0 (negativo)");

        // ----- OR -----
        $display("\n--- OR ---");
        testa(8'hAA, 8'h55, OP_OR,  8'hFF, 0,0,0,1, "AA|55=FF");
        testa(8'h00, 8'h00, OP_OR,  8'h00, 1,0,0,0, "00|00=00 (zero)");

        // ----- XOR -----
        $display("\n--- XOR ---");
        testa(8'hFF, 8'hFF, OP_XOR, 8'h00, 1,0,0,0, "FF^FF=00 (zero)");
        testa(8'hAA, 8'h55, OP_XOR, 8'hFF, 0,0,0,1, "AA^55=FF");
        testa(8'h3C, 8'h5A, OP_XOR, 8'h66, 0,0,0,0, "3C^5A=66");

        // ----- NOT -----
        $display("\n--- NOT ---");
        testa(8'h00, 8'hXX, OP_NOT, 8'hFF, 0,0,0,1, "~00=FF");
        testa(8'hFF, 8'hXX, OP_NOT, 8'h00, 1,0,0,0, "~FF=00 (zero)");
        testa(8'hA5, 8'hXX, OP_NOT, 8'h5A, 0,0,0,0, "~A5=5A");

        // ----- SHL -----
        $display("\n--- SHL ---");
        testa(8'h01, 8'hXX, OP_SHL, 8'h02, 0,0,0,0, "01<<1=02");
        testa(8'h80, 8'hXX, OP_SHL, 8'h00, 1,1,0,0, "80<<1=00 (carry+zero)");
        testa(8'h55, 8'hXX, OP_SHL, 8'hAA, 0,0,0,1, "55<<1=AA (negativo)");

        // ----- SHR -----
        $display("\n--- SHR ---");
        testa(8'h02, 8'hXX, OP_SHR, 8'h01, 0,0,0,0, "02>>1=01");
        testa(8'h01, 8'hXX, OP_SHR, 8'h00, 1,1,0,0, "01>>1=00 (carry+zero)");
        testa(8'hFF, 8'hXX, OP_SHR, 8'h7F, 0,1,0,0, "FF>>1=7F (carry)");

        $display("\n======================================================");
        $display(" Total: %0d/%0d testes corretos", testes-erros, testes);
        if (erros == 0)
            $display(">>> RESULTADO: APROVADO -- %0d/%0d testes passaram <<<",
                     testes, testes);
        else
            $display(">>> RESULTADO: REPROVADO -- %0d erro(s) <<<", erros);
        $display("=== Simulacao Concluida em %0t ===", $time);
        $finish;
    end

endmodule

docs/unidade7_cap5_desafio_romulo/dump_alu.vcd
$date
	Tue May 12 17:09:08 2026
$end
$version
	Icarus Verilog
$end
$timescale
	1ps
$end
$scope module tb_alu8_chip $end
$var wire 8 ! result [7:0] $end
$var wire 1 " flag_z $end
$var wire 1 # flag_v $end
$var wire 1 $ flag_n $end
$var wire 1 % flag_c $end
$var parameter 3 & OP_ADD $end
$var parameter 3 ' OP_AND $end
$var parameter 3 ( OP_NOT $end
$var parameter 3 ) OP_OR $end
$var parameter 3 * OP_SHL $end
$var parameter 3 + OP_SHR $end
$var parameter 3 , OP_SUB $end
$var parameter 3 - OP_XOR $end
$var reg 8 . a [7:0] $end
$var reg 8 / b [7:0] $end
$var reg 3 0 op [2:0] $end
$var integer 32 1 erros [31:0] $end
$var integer 32 2 testes [31:0] $end
$scope module dut $end
$var wire 8 3 a [7:0] $end
$var wire 8 4 b [7:0] $end
$var wire 3 5 op [2:0] $end
$var wire 8 6 result [7:0] $end
$var wire 1 " flag_z $end
$var wire 1 # flag_v $end
$var wire 1 $ flag_n $end
$var wire 1 % flag_c $end
$scope module u_alu $end
$var wire 8 7 a [7:0] $end
$var wire 8 8 b [7:0] $end
$var wire 1 # flag_v $end
$var wire 3 9 op [2:0] $end
$var wire 8 : result [7:0] $end
$var wire 1 ; res_msb $end
$var wire 1 " flag_z $end
$var wire 1 $ flag_n $end
$var wire 1 % flag_c $end
$var wire 1 < b_msb $end
$var wire 1 = a_msb $end
$var wire 1 > a_lsb $end
$var wire 7 ? a_lo7 [6:0] $end
$var wire 7 @ a_hi7 [6:0] $end
$var reg 9 A wide [8:0] $end
$upscope $end
$upscope $end
$scope task testa $end
$upscope $end
$upscope $end
$enddefinitions $end
$comment Show the parameter values. $end
$dumpall
b100 -
b1 ,
b111 +
b110 *
b11 )
b101 (
b10 '
b0 &
$end
#0
$dumpvars
b1000 A
b1 @
b11 ?
1>
0=
0<
0;
b1000 :
b0 9
b101 8
b11 7
b1000 6
b0 5
b101 4
b11 3
b0 2
b0 1
b0 0
b101 /
b11 .
0%
0$
0#
0"
b1000 !
$end
#2000
b0 !
b0 6
b0 :
1%
1"
b100000000 A
1=
b1111111 ?
b1111111 @
b1 /
b1 4
b1 8
b11111111 .
b11111111 3
b11111111 7
b1 2
#4000
1#
1;
b10000000 !
b10000000 6
b10000000 :
0%
0"
1$
b10000000 A
0=
b111111 @
b1111111 .
b1111111 3
b1111111 7
b10 2
#6000
1#
0;
b0 !
b0 6
b0 :
1%
1"
0$
1<
b100000000 A
1=
0>
b0 ?
b1000000 @
b10000000 /
b10000000 4
b10000000 8
b10000000 .
b10000000 3
b10000000 7
b11 2
#8000
0#
1;
b11010000 !
b11010000 6
b11010000 :
0%
0"
1$
0<
b11010000 A
b100000 ?
b1010000 @
b110000 /
b110000 4
b110000 8
b10100000 .
b10100000 3
b10100000 7
b100 2
#10000
0;
b101 !
b101 6
b101 :
1%
0$
b100000101 A
0=
b1000 ?
b100 @
b1 0
b1 5
b1 9
b11 /
b11 4
b11 8
b1000 .
b1000 3
b1000 7
b101 2
#12000
1;
b11111011 !
b11111011 6
b11111011 :
0%
1$
b11111011 A
1>
b11 ?
b1 @
b1000 /
b1000 4
b1000 8
b11 .
b11 3
b11 7
b110 2
#14000
b11111111 !
b11111111 6
b11111111 :
b11111111 A
0>
b0 ?
b0 @
b1 /
b1 4
b1 8
b0 .
b0 3
b0 7
b111 2
#16000
1#
0;
b1111111 !
b1111111 6
b1111111 :
1%
0$
b101111111 A
1=
b1000000 @
b10000000 .
b10000000 3
b10000000 7
b1000 2
#18000
0#
b0 !
b0 6
b0 :
1"
b100000000 A
0=
b1000000 ?
b100000 @
b1000000 /
b1000000 4
b1000000 8
b1000000 .
b1000000 3
b1000000 7
b1001 2
#20000
b1111 !
b1111 6
b1111 :
0%
0"
b1111 A
1=
1>
b1111111 ?
b1111111 @
b10 0
b10 5
b10 9
b1111 /
b1111 4
b1111 8
b11111111 .
b11111111 3
b11111111 7
b1010 2
#22000
b0 !
b0 6
b0 :
1"
b0 A
0>
b101010 ?
b1010101 @
b1010101 /
b1010101 4
b1010101 8
b10101010 .
b10101010 3
b10101010 7
b1011 2
#24000
1;
b11110000 !
b11110000 6
b11110000 :
0"
1$
1<
b11110000 A
b1110000 ?
b1111000 @
b11110000 /
b11110000 4
b11110000 8
b11110000 .
b11110000 3
b11110000 7
b1100 2
#26000
b11111111 !
b11111111 6
b11111111 :
0<
b11111111 A
b101010 ?
b1010101 @
b11 0
b11 5
b11 9
b1010101 /
b1010101 4
b1010101 8
b10101010 .
b10101010 3
b10101010 7
b1101 2
#28000
0;
b0 !
b0 6
b0 :
1"
0$
b0 A
0=
b0 ?
b0 @
b0 /
b0 4
b0 8
b0 .
b0 3
b0 7
b1110 2
#30000
1<
1=
1>
b1111111 ?
b1111111 @
b100 0
b100 5
b100 9
b11111111 /
b11111111 4
b11111111 8
b11111111 .
b11111111 3
b11111111 7
b1111 2
#32000
1;
b11111111 !
b11111111 6
b11111111 :
0"
1$
0<
b11111111 A
0>
b101010 ?
b1010101 @
b1010101 /
b1010101 4
b1010101 8
b10101010 .
b10101010 3
b10101010 7
b10000 2
#34000
0;
b1100110 !
b1100110 6
b1100110 :
0$
b1100110 A
0=
b111100 ?
b11110 @
b1011010 /
b1011010 4
b1011010 8
b111100 .
b111100 3
b111100 7
b10001 2
#36000
1;
b11111111 !
b11111111 6
b11111111 :
1$
x<
b11111111 A
b0 ?
b0 @
b101 0
b101 5
b101 9
bx /
bx 4
bx 8
b0 .
b0 3
b0 7
b10010 2
#38000
0;
b0 !
b0 6
b0 :
1"
0$
b0 A
1=
1>
b1111111 ?
b1111111 @
b11111111 .
b11111111 3
b11111111 7
b10011 2
#40000
b1011010 !
b1011010 6
b1011010 :
0"
b1011010 A
b100101 ?
b1010010 @
b10100101 .
b10100101 3
b10100101 7
b10100 2
#42000
b10 !
b10 6
b10 :
b10 A
0=
b1 ?
b0 @
b110 0
b110 5
b110 9
b1 .
b1 3
b1 7
b10101 2
#44000
b0 !
b0 6
b0 :
1%
1"
b100000000 A
1=
0>
b0 ?
b1000000 @
b10000000 .
b10000000 3
b10000000 7
b10110 2
#46000
1;
b10101010 !
b10101010 6
b10101010 :
0%
0"
1$
b10101010 A
0=
1>
b1010101 ?
b101010 @
b1010101 .
b1010101 3
b1010101 7
b10111 2
#48000
0;
b1 !
b1 6
b1 :
0$
b1 A
0>
b10 ?
b1 @
b111 0
b111 5
b111 9
b10 .
b10 3
b10 7
b11000 2
#50000
b0 !
b0 6
b0 :
1%
1"
b100000000 A
1>
b1 ?
b0 @
b1 .
b1 3
b1 7
b11001 2
#52000
b1111111 !
b1111111 6
b1111111 :
0"
b101111111 A
1=
b1111111 ?
b1111111 @
b11111111 .
b11111111 3
b11111111 7
b11010 2
#54000
b11011 2
