docs/unidade7_cap5_desafio/hamming_decoder.sv
// =============================================================================
// hamming_decoder.sv -- Decodificador/Corretor Hamming(7,4)
// HammingChip v1.0 | Unidade 7 | Capitulo 5 | PADIS
// Autor : Matheus Serrao Uchoa   Matricula: 22052633
// Prof. : Thiago Brito
// =============================================================================
// Recebe codeword de 7 bits (possivelmente com 1 erro de bit).
// Calcula a sindrome (3 bits) para localizar e corrigir o erro.
// Sindrome = {s4, s2, s1}:
//   s1 = c[0]^c[2]^c[4]^c[6]
//   s2 = c[1]^c[2]^c[5]^c[6]
//   s4 = c[3]^c[4]^c[5]^c[6]
// Valor da sindrome indica a posicao do bit errado (1-7), 0 = sem erro.
// Apos correcao, extrai os 4 bits de dados: {c[6],c[5],c[4],c[2]}.
// =============================================================================

module hamming_decoder (
    input  logic [6:0] code_in,    // codeword recebido (pode conter 1 erro)
    output logic [3:0] data_out,   // dados corrigidos
    output logic [2:0] syndrome,   // {s4,s2,s1}: posicao do erro (0=sem erro)
    output logic       error_flag  // 1 se erro detectado e corrigido
);

    logic [6:0] corrected;

    // Calculo da sindrome
    logic s1, s2, s4;
    assign s1 = code_in[0] ^ code_in[2] ^ code_in[4] ^ code_in[6];
    assign s2 = code_in[1] ^ code_in[2] ^ code_in[5] ^ code_in[6];
    assign s4 = code_in[3] ^ code_in[4] ^ code_in[5] ^ code_in[6];

    assign syndrome   = {s4, s2, s1};
    assign error_flag = (syndrome != 3'b000);

    // Correcao: inverte o bit na posicao indicada pela sindrome (1-indexed)
    always_comb begin
        corrected = code_in;
        if (error_flag) begin
            // syndrome contem a posicao (1 a 7) do bit errado
            // indice do array = posicao - 1
            case (syndrome)
                3'd1: corrected[0] = ~code_in[0];
                3'd2: corrected[1] = ~code_in[1];
                3'd3: corrected[2] = ~code_in[2];
                3'd4: corrected[3] = ~code_in[3];
                3'd5: corrected[4] = ~code_in[4];
                3'd6: corrected[5] = ~code_in[5];
                3'd7: corrected[6] = ~code_in[6];
                default: corrected = code_in;
            endcase
        end
    end

    // Extrai bits de dados do codeword corrigido: posicoes 3,5,6,7 (1-indexed)
    // = indices 2,4,5,6 (0-indexed) = {d4=c[6], d3=c[5], d2=c[4], d1=c[2]}
    assign data_out = {corrected[6], corrected[5], corrected[4], corrected[2]};

endmodule

docs/unidade7_cap5_desafio/hamming_encoder.sv
// =============================================================================
// hamming_encoder.sv -- Codificador Hamming(7,4)
// HammingChip v1.0 | Unidade 7 | Capitulo 5 | PADIS
// Autor : Matheus Serrao Uchoa   Matricula: 22052633
// Prof. : Thiago Brito
// =============================================================================
// Codifica 4 bits de dados em 7 bits (3 bits de paridade adicionados).
// Estrutura do codeword (indice 0 = LSB):
//   [6]  [5]  [4]  [3]  [2]  [1]  [0]
//    d4   d3   d2   p4   d1   p2   p1
//
// Calculos de paridade:
//   p1 (pos 1) = d1 ^ d2 ^ d4     (cobre posicoes 1,3,5,7)
//   p2 (pos 2) = d1 ^ d3 ^ d4     (cobre posicoes 2,3,6,7)
//   p4 (pos 4) = d2 ^ d3 ^ d4     (cobre posicoes 4,5,6,7)
// =============================================================================

module hamming_encoder (
    input  logic [3:0] data_in,    // [3]=d4  [2]=d3  [1]=d2  [0]=d1
    output logic [6:0] code_out    // [6]=d4 [5]=d3 [4]=d2 [3]=p4 [2]=d1 [1]=p2 [0]=p1
);

    logic d1, d2, d3, d4;
    logic p1, p2, p4;

    assign {d4, d3, d2, d1} = data_in;

    assign p1 = d1 ^ d2 ^ d4;   // paridade impar sobre posicoes 1,3,5,7
    assign p2 = d1 ^ d3 ^ d4;   // paridade impar sobre posicoes 2,3,6,7
    assign p4 = d2 ^ d3 ^ d4;   // paridade impar sobre posicoes 4,5,6,7

    assign code_out = {d4, d3, d2, p4, d1, p2, p1};

endmodule

docs/unidade7_cap5_desafio/hamming_chip_top.sv
// =============================================================================
// hamming_chip_top.sv -- Top-level: HammingChip v1.0
// Codec Hamming(7,4) com Correcao de Erros de 1 bit
// Unidade 7 | Capitulo 5 | PADIS
// Autor : Matheus Serrao Uchoa   Matricula: 22052633
// Prof. : Thiago Brito
// =============================================================================
// Hierarquia:
//   hamming_chip_top
//   ├── hamming_encoder  -- codifica 4->7 bits (combinacional)
//   └── hamming_decoder  -- decodifica/corrige 7->4 bits (combinacional)
//
// Especificacoes:
//   Processo : CMOS 0.35um | VDD = 3.3V
//   Funcao   : Codec ECC Hamming(7,4) -- detecta e corrige 1 erro de bit
//   Latencia : 0 ciclos (logica puramente combinacional)
//   Aplicacao: Memoria ECC, comunicacao espacial, barramento seguro
// =============================================================================

module hamming_chip_top (
    input  logic [3:0] data_in,      // dados a codificar
    output logic [6:0] encoded,      // codeword codificado (7 bits)

    input  logic [6:0] received,     // codeword recebido (canal ruidoso)
    output logic [3:0] data_out,     // dados recuperados (corrigidos)
    output logic [2:0] syndrome,     // {s4,s2,s1}: sindrome do erro
    output logic       error_flag    // 1 se erro foi detectado/corrigido
);

    hamming_encoder u_enc (
        .data_in  (data_in),
        .code_out (encoded)
    );

    hamming_decoder u_dec (
        .code_in    (received),
        .data_out   (data_out),
        .syndrome   (syndrome),
        .error_flag (error_flag)
    );

endmodule

docs/unidade7_cap5_desafio/tb_hamming_chip.sv
// =============================================================================
// tb_hamming_chip.sv -- Testbench: HammingChip v1.0 (Golden Model)
// Unidade 7 | Capitulo 5 | PADIS
// Autor : Matheus Serrao Uchoa   Matricula: 22052633
// =============================================================================
`timescale 1ns/1ps

module tb_hamming_chip;

    logic [3:0] data_in;
    logic [6:0] encoded;
    logic [6:0] received;
    logic [3:0] data_out;
    logic [2:0] syndrome;
    logic       error_flag;

    int erros  = 0;
    int testes = 0;

    hamming_chip_top dut (.*);

    // Testa codificacao + decodificacao sem erro (round-trip)
    task automatic testa_roundtrip(input logic [3:0] din);
        data_in  = din;
        #2;
        received = encoded;    // transmite sem erro
        #2;
        testes++;
        if (data_out !== din || error_flag !== 1'b0) begin
            $display("  [FALHA-RT] data=%04b => enc=%07b => dec=%04b ErrFlag=%b",
                     din, encoded, data_out, error_flag);
            erros++;
        end else begin
            $display("  [OK-RT]   data=%04b => codeword=%07b => dec=%04b (sem erro)",
                     din, encoded, data_out);
        end
    endtask

    // Injeta erro em bit_pos e verifica correcao
    task automatic testa_correcao(input logic [3:0] din, input int bit_pos);
        data_in = din;
        #2;
        received = encoded ^ (7'b1 << bit_pos);  // injeta 1 erro
        #2;
        testes++;
        if (data_out !== din || error_flag !== 1'b1) begin
            $display("  [FALHA-ERR] data=%04b | bit=%0d | dec=%04b | syn=%03b | flag=%b",
                     din, bit_pos, data_out, syndrome, error_flag);
            erros++;
        end else begin
            $display("  [OK-ERR]  data=%04b | bit=%0d | syn=%03b=%0d | corrigido OK",
                     din, bit_pos, syndrome, syndrome);
        end
    endtask

    initial begin
        $dumpfile("dump_hamming.vcd");
        $dumpvars(0, tb_hamming_chip);

        $display("======================================================");
        $display(" HammingChip v1.0 -- Codec Hamming(7,4)");
        $display(" Simulacao Funcional (Golden Model)");
        $display(" Processo: CMOS 0.35um | VDD=3.3V");
        $display("======================================================");

        // Fase 1: Round-trip todos os 16 valores
        $display("\n--- Fase 1: Round-trip (16 vetores, sem erro) ---");
        testa_roundtrip(4'b0000); testa_roundtrip(4'b0001);
        testa_roundtrip(4'b0010); testa_roundtrip(4'b0011);
        testa_roundtrip(4'b0100); testa_roundtrip(4'b0101);
        testa_roundtrip(4'b0110); testa_roundtrip(4'b0111);
        testa_roundtrip(4'b1000); testa_roundtrip(4'b1001);
        testa_roundtrip(4'b1010); testa_roundtrip(4'b1011);
        testa_roundtrip(4'b1100); testa_roundtrip(4'b1101);
        testa_roundtrip(4'b1110); testa_roundtrip(4'b1111);

        // Fase 2: Correcao em todas as 7 posicoes (2 dados diferentes)
        $display("\n--- Fase 2: Correcao de erro em cada posicao (data=1011) ---");
        testa_correcao(4'b1011, 0); testa_correcao(4'b1011, 1);
        testa_correcao(4'b1011, 2); testa_correcao(4'b1011, 3);
        testa_correcao(4'b1011, 4); testa_correcao(4'b1011, 5);
        testa_correcao(4'b1011, 6);

        $display("\n--- Fase 2b: Correcao de erro em cada posicao (data=0101) ---");
        testa_correcao(4'b0101, 0); testa_correcao(4'b0101, 1);
        testa_correcao(4'b0101, 2); testa_correcao(4'b0101, 3);
        testa_correcao(4'b0101, 4); testa_correcao(4'b0101, 5);
        testa_correcao(4'b0101, 6);

        $display("\n======================================================");
        $display(" Total: %0d/%0d testes corretos", testes-erros, testes);
        if (erros == 0)
            $display(">>> RESULTADO: APROVADO -- %0d/%0d testes passaram <<<",
                     testes, testes);
        else
            $display(">>> RESULTADO: REPROVADO -- %0d erro(s) <<<", erros);
        $display("=== Simulacao Concluida em %0t ===", $time);
        $finish;
    end

endmodule

docs/unidade7_cap5_desafio/dump_hamming.vcd
$date
	Tue May 12 14:18:07 2026
$end
$version
	Icarus Verilog
$end
$timescale
	1ps
$end
$scope module tb_hamming_chip $end
$var wire 3 ! syndrome [2:0] $end
$var wire 1 " error_flag $end
$var wire 7 # encoded [6:0] $end
$var wire 4 $ data_out [3:0] $end
$var reg 4 % data_in [3:0] $end
$var reg 7 & received [6:0] $end
$var integer 32 ' erros [31:0] $end
$var integer 32 ( testes [31:0] $end
$scope module dut $end
$var wire 4 ) data_in [3:0] $end
$var wire 7 * received [6:0] $end
$var wire 3 + syndrome [2:0] $end
$var wire 1 " error_flag $end
$var wire 7 , encoded [6:0] $end
$var wire 4 - data_out [3:0] $end
$scope module u_dec $end
$var wire 7 . code_in [6:0] $end
$var wire 1 / s1 $end
$var wire 1 0 s2 $end
$var wire 1 1 s4 $end
$var wire 3 2 syndrome [2:0] $end
$var wire 1 " error_flag $end
$var wire 4 3 data_out [3:0] $end
$var reg 7 4 corrected [6:0] $end
$upscope $end
$scope module u_enc $end
$var wire 4 5 data_in [3:0] $end
$var wire 1 6 p1 $end
$var wire 1 7 p2 $end
$var wire 1 8 p4 $end
$var wire 1 9 d4 $end
$var wire 1 : d3 $end
$var wire 1 ; d2 $end
$var wire 1 < d1 $end
$var wire 7 = code_out [6:0] $end
$upscope $end
$upscope $end
$scope task testa_correcao $end
$upscope $end
$scope task testa_roundtrip $end
$upscope $end
$upscope $end
$enddefinitions $end
$comment Show the parameter values. $end
$dumpall
$end
#0
$dumpvars
b0 =
0<
0;
0:
09
08
07
06
b0 5
bx 4
bx 3
bx 2
x1
x0
x/
bx .
bx -
b0 ,
bx +
bx *
b0 )
b0 (
b0 '
bx &
b0 %
bx $
b0 #
x"
bx !
$end
#2000
0"
0/
00
b0 !
b0 +
b0 2
01
b0 $
b0 -
b0 3
b0 4
b0 &
b0 *
b0 .
#4000
17
16
b111 #
b111 ,
b111 =
1<
b1 %
b1 )
b1 5
b1 (
#6000
b1 $
b1 -
b1 3
b111 4
b111 &
b111 *
b111 .
#8000
18
07
1;
b11001 #
b11001 ,
b11001 =
0<
b10 %
b10 )
b10 5
b10 (
#10000
0"
b0 !
b0 +
b0 2
0/
b10 $
b10 -
b10 3
b11001 4
b11001 &
b11001 *
b11001 .
#12000
17
06
b11110 #
b11110 ,
b11110 =
1<
b11 %
b11 )
b11 5
b11 (
#14000
b11 $
b11 -
b11 3
b11110 4
b11110 &
b11110 *
b11110 .
#16000
1:
0;
b101010 #
b101010 ,
b101010 =
0<
b100 %
b100 )
b100 5
b100 (
#18000
0/
00
0"
b0 !
b0 +
b0 2
01
b100 $
b100 -
b100 3
b101010 4
b101010 &
b101010 *
b101010 .
#20000
07
16
b101101 #
b101101 ,
b101101 =
1<
b101 %
b101 )
b101 5
b101 (
#22000
b101 $
b101 -
b101 3
b101101 4
b101101 &
b101101 *
b101101 .
#24000
08
17
1;
b110011 #
b110011 ,
b110011 =
0<
b110 %
b110 )
b110 5
b110 (
#26000
0"
b0 !
b0 +
b0 2
0/
b110 $
b110 -
b110 3
b110011 4
b110011 &
b110011 *
b110011 .
#28000
07
06
b110100 #
b110100 ,
b110100 =
1<
b111 %
b111 )
b111 5
b111 (
#30000
b111 $
b111 -
b111 3
b110100 4
b110100 &
b110100 *
b110100 .
#32000
18
17
16
19
0:
0;
b1001011 #
b1001011 ,
b1001011 =
0<
b1000 %
b1000 )
b1000 5
b1000 (
#34000
b1000 $
b1000 -
b1000 3
0/
00
0"
b0 !
b0 +
b0 2
01
b1001011 4
b1001011 &
b1001011 *
b1001011 .
#36000
07
06
b1001100 #
b1001100 ,
b1001100 =
1<
b1001 %
b1001 )
b1001 5
b1001 (
#38000
b1001 $
b1001 -
b1001 3
b1001100 4
b1001100 &
b1001100 *
b1001100 .
#40000
08
17
1;
b1010010 #
b1010010 ,
b1010010 =
0<
b1010 %
b1010 )
b1010 5
b1010 (
#42000
0"
b0 !
b0 +
b0 2
0/
b1010 $
b1010 -
b1010 3
b1010010 4
b1010010 &
b1010010 *
b1010010 .
#44000
07
16
b1010101 #
b1010101 ,
b1010101 =
1<
b1011 %
b1011 )
b1011 5
b1011 (
#46000
b1011 $
b1011 -
b1011 3
b1010101 4
b1010101 &
b1010101 *
b1010101 .
#48000
1:
0;
b1100001 #
b1100001 ,
b1100001 =
0<
b1100 %
b1100 )
b1100 5
b1100 (
#50000
0/
00
0"
b0 !
b0 +
b0 2
01
b1100 $
b1100 -
b1100 3
b1100001 4
b1100001 &
b1100001 *
b1100001 .
#52000
17
06
b1100110 #
b1100110 ,
b1100110 =
1<
b1101 %
b1101 )
b1101 5
b1101 (
#54000
b1101 $
b1101 -
b1101 3
b1100110 4
b1100110 &
b1100110 *
b1100110 .
#56000
18
07
1;
b1111000 #
b1111000 ,
b1111000 =
0<
b1110 %
b1110 )
b1110 5
b1110 (
#58000
0"
b0 !
b0 +
b0 2
0/
b1110 $
b1110 -
b1110 3
b1111000 4
b1111000 &
b1111000 *
b1111000 .
#60000
17
16
b1111111 #
b1111111 ,
b1111111 =
1<
b1111 %
b1111 )
b1111 5
b1111 (
#62000
b1111 $
b1111 -
b1111 3
b1111111 4
b1111111 &
b1111111 *
b1111111 .
#64000
08
07
b1010101 #
b1010101 ,
b1010101 =
0:
b1011 %
b1011 )
b1011 5
b10000 (
#66000
1/
00
1"
b1 !
b1 +
b1 2
01
b1011 $
b1011 -
b1011 3
b1010101 4
b1010100 &
b1010100 *
b1010100 .
#68000
b10001 (
#70000
0/
b10 !
b10 +
b10 2
10
b1010101 4
b1010111 &
b1010111 *
b1010111 .
#72000
b10010 (
#74000
b11 !
b11 +
b11 2
1/
b1011 $
b1011 -
b1011 3
b1010101 4
b1010001 &
b1010001 *
b1010001 .
#76000
b10011 (
#78000
0/
00
b100 !
b100 +
b100 2
11
b1011 $
b1011 -
b1011 3
b1010101 4
b1011101 &
b1011101 *
b1011101 .
#80000
b10100 (
#82000
b101 !
b101 +
b101 2
1/
b1011 $
b1011 -
b1011 3
b1010101 4
b1000101 &
b1000101 *
b1000101 .
#84000
b10101 (
#86000
0/
10
b110 !
b110 +
b110 2
11
b1011 $
b1011 -
b1011 3
b1010101 4
b1110101 &
b1110101 *
b1110101 .
#88000
b10110 (
#90000
b1011 $
b1011 -
b1011 3
1/
1"
10
b111 !
b111 +
b111 2
11
b1010101 4
b10101 &
b10101 *
b10101 .
#92000
18
09
1:
b101101 #
b101101 ,
b101101 =
0;
b101 %
b101 )
b101 5
b10111 (
#94000
1"
1/
00
b1 !
b1 +
b1 2
01
b101 $
b101 -
b101 3
b101101 4
b101100 &
b101100 *
b101100 .
#96000
b11000 (
#98000
0/
b10 !
b10 +
b10 2
10
b101101 4
b101111 &
b101111 *
b101111 .
#100000
b11001 (
#102000
b11 !
b11 +
b11 2
1/
b101 $
b101 -
b101 3
b101101 4
b101001 &
b101001 *
b101001 .
#104000
b11010 (
#106000
0/
00
b100 !
b100 +
b100 2
11
b101 $
b101 -
b101 3
b101101 4
b100101 &
b100101 *
b100101 .
#108000
b11011 (
#110000
b101 !
b101 +
b101 2
1/
b101 $
b101 -
b101 3
b101101 4
b111101 &
b111101 *
b111101 .
#112000
b11100 (
#114000
0/
10
b110 !
b110 +
b110 2
11
b101 $
b101 -
b101 3
b101101 4
b1101 &
b1101 *
b1101 .
#116000
b11101 (
#118000
b101 $
b101 -
b101 3
1/
1"
10
b111 !
b111 +
b111 2
11
b101101 4
b1101101 &
b1101101 *
b1101101 .
#120000
b11110 (
